odoo/addons/sale_order_ubl/README.rst
odoo/addons/sale_order_ubl/__init__.py
odoo/addons/sale_order_ubl/__manifest__.py
odoo/addons/sale_order_ubl/i18n/hr.po
odoo/addons/sale_order_ubl/i18n/sale_order_ubl.pot
odoo/addons/sale_order_ubl/models/__init__.py
odoo/addons/sale_order_ubl/models/report.py
odoo/addons/sale_order_ubl/models/sale.py
odoo/addons/sale_order_ubl/readme/CONTRIBUTORS.rst
odoo/addons/sale_order_ubl/readme/DESCRIPTION.rst
odoo/addons/sale_order_ubl/static/description/icon.png
odoo/addons/sale_order_ubl/static/description/index.html
odoo/addons/sale_order_ubl/tests/__init__.py
odoo/addons/sale_order_ubl/tests/test_ubl_generate.py
odoo13_addon_sale_order_ubl-13.0.1.1.0.dist-info/METADATA
odoo13_addon_sale_order_ubl-13.0.1.1.0.dist-info/WHEEL
odoo13_addon_sale_order_ubl-13.0.1.1.0.dist-info/top_level.txt
odoo13_addon_sale_order_ubl-13.0.1.1.0.dist-info/RECORD
